fmp/__init__.py
fmp/cli.py
fmp/fmp.py
fmp-0.3.3.dist-info/entry_points.txt
fmp-0.3.3.dist-info/LICENSE
fmp-0.3.3.dist-info/WHEEL
fmp-0.3.3.dist-info/METADATA
fmp-0.3.3.dist-info/RECORD
