Metadata-Version: 2.1
Name: fmp
Version: 0.3.3
Summary: Formats python files with properly sorted import statemnts
License: MIT
Author: Alyetama
Author-email: malyetama@pm.me
Requires-Python: >=3.6,<4.0
Classifier: License :: OSI Approved :: MIT License
Classifier: Programming Language :: Python :: 3
Classifier: Programming Language :: Python :: 3.10
Classifier: Programming Language :: Python :: 3.6
Classifier: Programming Language :: Python :: 3.7
Classifier: Programming Language :: Python :: 3.8
Classifier: Programming Language :: Python :: 3.9
Requires-Dist: autoflake (>=1.4,<2.0)
Requires-Dist: beautifulsoup4 (>=4.10.0,<5.0.0)
Requires-Dist: requests (>=2.27.1,<3.0.0)
Requires-Dist: rich (>=10.11.0,<11.0.0)
Requires-Dist: yapf (>=0.32.0,<0.33.0)
